[
    {
        "title": "Beef Salpicao",
        "recipe-link": "https://www.kawalingpinoy.com/beef-salpicao/",
        "image": "https://www.kawalingpinoy.com/wp-content/uploads/2014/10/beef-salpicao-8-680x884.jpg",
        "meal": "appetizer"
    },
    {
        "title": "Rellenong Alimango",
        "recipe-link": "https://www.kawalingpinoy.com/rellenong-alimango/",
        "image": "https://www.kawalingpinoy.com/wp-content/uploads/2014/12/rellenong-alimango-3-680x884.jpg",
        "meal": "appetizer"
    },
    {
        "title": "Pinsec Frito",
        "recipe-link": "https://www.kawalingpinoy.com/pinsec-frito/",
        "image": "https://www.kawalingpinoy.com/wp-content/uploads/2014/06/pinsec-frito-1-680x884.jpg",
        "meal": "appetizer"
    },
    {
        "title": "Banana Heart Burger",
        "recipe-link": "https://www.kawalingpinoy.com/banana-heart-burger/",
        "image": "https://www.kawalingpinoy.com/wp-content/uploads/2017/05/banana-heart-burger-3-680x884.jpg",
        "meal": "appetizer"
    },
    {
        "title": "Baby Back Ribs with Adobo Glaze",
        "recipe-link": "https://www.kawalingpinoy.com/baby-back-ribs-adobo-glaze/",
        "image": "https://www.kawalingpinoy.com/wp-content/uploads/2017/04/baby-back-ribs-adobo-glaze-1-680x884.jpg",
        "meal": "appetizer"
    },
    {
        "title": "Filipino Pork Barbecue",
        "recipe-link": "https://www.kawalingpinoy.com/filipino-pork-barbecue/",
        "image": "https://www.kawalingpinoy.com/wp-content/uploads/2018/06/filipino-style-pork-bbq-1-680x884.jpg",
        "meal": "appetizer"
    },
    {
        "title": "Camaron Rebosado",
        "recipe-link": "https://www.kawalingpinoy.com/camaron-rebosado/",
        "image": "https://www.kawalingpinoy.com/wp-content/uploads/2014/02/camaron-rebosado-1-680x884.jpg",
        "meal": "appetizer"
    },
    {
        "title": "Lumpiang Puso ng Saging",
        "recipe-link": "https://www.kawalingpinoy.com/lumpiang-puso-ng-saging/",
        "image": "https://www.kawalingpinoy.com/wp-content/uploads/2014/06/lumpiang-puso-ng-saging-1-680x884.jpg",
        "meal": "appetizer"
    },
    {
        "title": "Ukoy na Dilis",
        "recipe-link": "https://www.kawalingpinoy.com/ukoy-na-dilis/",
        "image": "https://www.kawalingpinoy.com/wp-content/uploads/2016/06/ukoy-dilis-7-680x884.jpg",
        "meal": "appetizer"
    },
    {
        "title": "Kwek-kwek",
        "recipe-link": "https://www.kawalingpinoy.com/kwek-kwek/",
        "image": "https://www.kawalingpinoy.com/wp-content/uploads/2019/07/kwek-kwek-14-680x884.jpg",
        "meal": "appetizer"
    },
    {
        "title": "Garlic Butter Fried Frog Legs",
        "recipe-link": "https://www.kawalingpinoy.com/garlic-butter-fried-frog-legs/",
        "image": "https://www.kawalingpinoy.com/wp-content/uploads/2013/03/Garlic-butter-fried-legs-4-680x884.jpg",
        "meal": "appetizer"
    },
    {
        "title": "Beef Empanada",
        "recipe-link": "https://www.kawalingpinoy.com/beef-empanada/",
        "image": "https://www.kawalingpinoy.com/wp-content/uploads/2019/03/beef-empanada-11-680x884.jpg",
        "meal": "appetizer"
    },
    {
        "title": "Ahi Shoyu Poke",
        "recipe-link": "https://www.kawalingpinoy.com/ahi-shoyu-poke/",
        "image": "https://www.kawalingpinoy.com/wp-content/uploads/2017/06/ahi-shoyu-poke-8-680x884.jpg",
        "meal": "appetizer"
    },
    {
        "title": "Ham and Cheese Bread Rolls",
        "recipe-link": "https://www.kawalingpinoy.com/ham-cheese-bread-rolls/",
        "image": "https://www.kawalingpinoy.com/wp-content/uploads/2019/11/ham-cheese-bread-rolls-4-680x884.jpg",
        "meal": "appetizer"
    },
    {
        "title": "Lumpia Shanghai",
        "recipe-link": "https://www.kawalingpinoy.com/lumpia-shanghai/",
        "image": "https://www.kawalingpinoy.com/wp-content/uploads/2017/06/crispy-lumpiang-shanghai-680x884.jpg",
        "meal": "appetizer"
    },
    {
        "title": "Adobong Talaba",
        "recipe-link": "https://www.kawalingpinoy.com/adobong-talaba/",
        "image": "https://www.kawalingpinoy.com/wp-content/uploads/2018/04/adobo-talaba-680x884.jpg",
        "meal": "appetizer"
    },
    {
        "title": "Spicy Tahong",
        "recipe-link": "https://www.kawalingpinoy.com/spicy-tahong/",
        "image": "https://www.kawalingpinoy.com/wp-content/uploads/2014/08/spicy-tahong-3-680x884.jpg",
        "meal": "appetizer"
    },
    {
        "title": "Pinakupsan",
        "recipe-link": "https://www.kawalingpinoy.com/pinakupsan/",
        "image": "https://www.kawalingpinoy.com/wp-content/uploads/2015/07/Visayan-pinakupsan-3-680x884.jpg",
        "meal": "appetizer"
    },
    {
        "title": "Sizzling Sisig",
        "recipe-link": "https://www.kawalingpinoy.com/sisig/",
        "image": "https://www.kawalingpinoy.com/wp-content/uploads/2018/12/sisig-2-680x884.jpg",
        "meal": "appetizer"
    },
    {
        "title": "Tikoy",
        "recipe-link": "https://www.kawalingpinoy.com/tikoy/",
        "image": "https://www.kawalingpinoy.com/wp-content/uploads/2022/02/homemade-tikoy-3-680x884.jpg",
        "meal": "appetizer"
    },
    {
        "title": "Bopis",
        "recipe-link": "https://www.kawalingpinoy.com/bopis/",
        "image": "https://www.kawalingpinoy.com/wp-content/uploads/2018/04/kapampangan-bopis-1-680x884.jpg",
        "meal": "appetizer"
    },
    {
        "title": "Tokwa't Baboy",
        "recipe-link": "https://www.kawalingpinoy.com/tokwat-baboy/",
        "image": "https://www.kawalingpinoy.com/wp-content/uploads/2014/05/tokwa-baboy-2-680x884.jpg",
        "meal": "appetizer"
    },
    {
        "title": "Chinese Pearl Balls",
        "recipe-link": "https://www.kawalingpinoy.com/chinese-pearl-balls/",
        "image": "https://www.kawalingpinoy.com/wp-content/uploads/2014/10/pearl-balls-2-680x884.jpg",
        "meal": "appetizer"
    },
    {
        "title": "Pineapple Salsa",
        "recipe-link": "https://www.kawalingpinoy.com/pineapple-salsa/",
        "image": "https://www.kawalingpinoy.com/wp-content/uploads/2015/08/pineapple-salsa-1-1-680x884.jpg",
        "meal": "appetizer"
    },
    {
        "title": "Rellenong Hipon",
        "recipe-link": "https://www.kawalingpinoy.com/rellenong-hipon/",
        "image": "https://www.kawalingpinoy.com/wp-content/uploads/2018/02/rellenong-hipon-4-680x884.jpg",
        "meal": "appetizer"
    },
    {
        "title": "Fried Okra",
        "recipe-link": "https://www.kawalingpinoy.com/fried-okra/",
        "image": "https://www.kawalingpinoy.com/wp-content/uploads/2015/03/crispy-fried-okra-1-680x884.jpg",
        "meal": "appetizer"
    },
    {
        "title": "Sinampalukang Kambing",
        "recipe-link": "https://www.kawalingpinoy.com/sinampalukang-kambing/",
        "image": "https://www.kawalingpinoy.com/wp-content/uploads/2015/11/sinampalukang-kambing-8-1200-680x884.jpg",
        "meal": "appetizer"
    },
    {
        "title": "Kalderetang Kambing",
        "recipe-link": "https://www.kawalingpinoy.com/kalderetang-kambing/",
        "image": "https://www.kawalingpinoy.com/wp-content/uploads/2015/09/kalderetang-kambing-2-680x884.jpg",
        "meal": "appetizer"
    },
    {
        "title": "Baked Cheese Shrimp",
        "recipe-link": "https://www.kawalingpinoy.com/baked-cheese-shrimp/",
        "image": "https://www.kawalingpinoy.com/wp-content/uploads/2017/09/easy-baked-cheese-shrimp-3-680x884.jpg",
        "meal": "appetizer"
    },
    {
        "title": "Chicken Skin Chicharon",
        "recipe-link": "https://www.kawalingpinoy.com/chicken-skin-chicharon/",
        "image": "https://www.kawalingpinoy.com/wp-content/uploads/2014/09/chicken-chicharon-2-680x884.jpg",
        "meal": "appetizer"
    },
    {
        "title": "Coconut Shrimp",
        "recipe-link": "https://www.kawalingpinoy.com/coconut-shrimp/",
        "image": "https://www.kawalingpinoy.com/wp-content/uploads/2015/02/coconut-shrimp-4-680x884.jpg",
        "meal": "appetizer"
    },
    {
        "title": "Crispy Fried Smelt Fish",
        "recipe-link": "https://www.kawalingpinoy.com/crispy-fried-smelt-fish/",
        "image": "https://www.kawalingpinoy.com/wp-content/uploads/2016/04/crispy-smelt-fish-5-680x884.jpg",
        "meal": "appetizer"
    },
    {
        "title": "Crispy Tuna Shanghai",
        "recipe-link": "https://www.kawalingpinoy.com/crispy-tuna-shanghai/",
        "image": "https://www.kawalingpinoy.com/wp-content/uploads/2021/08/crispy-tuna-shanghai-3-680x884.jpg",
        "meal": "appetizer"
    },
    {
        "title": "Crispy Tuna Pies",
        "recipe-link": "https://www.kawalingpinoy.com/crispy-tuna-pies/",
        "image": "https://www.kawalingpinoy.com/wp-content/uploads/2021/08/crispy-tuna-pie-4-680x884.jpg",
        "meal": "appetizer"
    },
    {
        "title": "Sisig Pusit",
        "recipe-link": "https://www.kawalingpinoy.com/sisig-pusit/",
        "image": "https://www.kawalingpinoy.com/wp-content/uploads/2016/08/sisig-pusit-5-680x884.jpg",
        "meal": "appetizer"
    },
    {
        "title": "Dinakdakan",
        "recipe-link": "https://www.kawalingpinoy.com/dinakdakan/",
        "image": "https://www.kawalingpinoy.com/wp-content/uploads/2015/11/dinakdakan-6-680x884.jpg",
        "meal": "appetizer"
    },
    {
        "title": "Banana Meat",
        "recipe-link": "https://www.kawalingpinoy.com/banana-meat/",
        "image": "https://www.kawalingpinoy.com/wp-content/uploads/2018/06/banana-meat-4-680x884.jpg",
        "meal": "appetizer"
    },
    {
        "title": "Crispy Sisig",
        "recipe-link": "https://www.kawalingpinoy.com/crispy-sisig/",
        "image": "https://www.kawalingpinoy.com/wp-content/uploads/2017/03/crispy-sisig-5-680x884.jpg",
        "meal": "appetizer"
    },
    {
        "title": "Crispy Tahong (Deep-Fried Mussels)",
        "recipe-link": "https://www.kawalingpinoy.com/crispy-tahong-deep-fried-mussels/",
        "image": "https://www.kawalingpinoy.com/wp-content/uploads/2013/06/crispy-tahong-1-680x884.jpg",
        "meal": "appetizer"
    },
    {
        "title": "Loslos",
        "recipe-link": "https://www.kawalingpinoy.com/loslos/",
        "image": "https://www.kawalingpinoy.com/wp-content/uploads/2014/09/crispy-loslos-3-680x884.jpg",
        "meal": "appetizer"
    },
    {
        "title": "Sriracha Shrimp Scampi",
        "recipe-link": "https://www.kawalingpinoy.com/sriracha-shrimp-scampi/",
        "image": "https://www.kawalingpinoy.com/wp-content/uploads/2016/11/sriracha-shrimp-7-680x884.jpg",
        "meal": "appetizer"
    },
    {
        "title": "Lechon Kawali",
        "recipe-link": "https://www.kawalingpinoy.com/lechon-kawali/",
        "image": "https://www.kawalingpinoy.com/wp-content/uploads/2014/10/crispy-lechon-kawali-4-680x884.jpg",
        "meal": "appetizer"
    },
    {
        "title": "Chinese Boiled Peanuts",
        "recipe-link": "https://www.kawalingpinoy.com/chinese-boiled-peanuts/",
        "image": "https://www.kawalingpinoy.com/wp-content/uploads/2015/05/chinese-boiled-peanuts-8-680x884.jpg",
        "meal": "appetizer"
    },
    {
        "title": "Crispy Breaded Shrimp",
        "recipe-link": "https://www.kawalingpinoy.com/crispy-breaded-shrimp/",
        "image": "https://www.kawalingpinoy.com/wp-content/uploads/2018/07/crispy-shrimp-4-680x884.jpg",
        "meal": "appetizer"
    },
    {
        "title": "Inihaw na Pusit (Grilled Squid)",
        "recipe-link": "https://www.kawalingpinoy.com/inihaw-na-pusit-grilled-squid/",
        "image": "https://www.kawalingpinoy.com/wp-content/uploads/2013/06/inihaw-na-pusit-8.jpg",
        "meal": "appetizer"
    },
    {
        "title": "Adobong Paa nang Manok (Chicken Feet Adobo)",
        "recipe-link": "https://www.kawalingpinoy.com/adobong-paa-nang-manok-chicken-feet-adobo/",
        "image": "https://www.kawalingpinoy.com/wp-content/uploads/2013/06/adobong-paa-ng-manok-5-680x884.jpg",
        "meal": "appetizer"
    },
    {
        "title": "Tamarind Chicken Wings",
        "recipe-link": "https://www.kawalingpinoy.com/tamarind-chicken-wings/",
        "image": "https://www.kawalingpinoy.com/wp-content/uploads/2020/11/tamarind-chicken-wings-8-680x884.jpg",
        "meal": "appetizer"
    },
    {
        "title": "Sushi Bake",
        "recipe-link": "https://www.kawalingpinoy.com/sushi-bake/",
        "image": "https://www.kawalingpinoy.com/wp-content/uploads/2020/09/baked-sushi-4-1-680x884.jpg",
        "meal": "appetizer"
    },
    {
        "title": "Cheese Dog Bread Rolls",
        "recipe-link": "https://www.kawalingpinoy.com/cheese-dog-bread-rolls/",
        "image": "https://www.kawalingpinoy.com/wp-content/uploads/2020/08/cheese-hot-dog-bread-rolls-3-680x884.jpg",
        "meal": "appetizer"
    },
    {
        "title": "Ukoy",
        "recipe-link": "https://www.kawalingpinoy.com/ukoy/",
        "image": "https://www.kawalingpinoy.com/wp-content/uploads/2020/05/crispy-ukoy-2-680x884.jpg",
        "meal": "appetizer"
    },
    {
        "title": "Sizzling Gambas",
        "recipe-link": "https://www.kawalingpinoy.com/sizzling-gambas/",
        "image": "https://www.kawalingpinoy.com/wp-content/uploads/2020/05/sizzling-gambas-with-garlic-6-680x884.jpg",
        "meal": "appetizer"
    },
    {
        "title": "Cheese Sticks",
        "recipe-link": "https://www.kawalingpinoy.com/cheese-sticks/",
        "image": "https://www.kawalingpinoy.com/wp-content/uploads/2020/05/crispy-cheese-sticks-4-680x884.jpg",
        "meal": "appetizer"
    },
    {
        "title": "Spam Musubi",
        "recipe-link": "https://www.kawalingpinoy.com/spam-musubi/",
        "image": "https://www.kawalingpinoy.com/wp-content/uploads/2020/03/Hawaiian-spam-musubi-3-680x884.jpg",
        "meal": "appetizer"
    },
    {
        "title": "Sizzling Tofu",
        "recipe-link": "https://www.kawalingpinoy.com/sizzling-tofu/",
        "image": "https://www.kawalingpinoy.com/wp-content/uploads/2019/11/sisig-tofu-2-680x884.jpg",
        "meal": "appetizer"
    },
    {
        "title": "Nilasing na Hipon",
        "recipe-link": "https://www.kawalingpinoy.com/nilasing-na-hipon/",
        "image": "https://www.kawalingpinoy.com/wp-content/uploads/2019/07/crispy-nilasing-na-hipon-6-680x884.jpg",
        "meal": "appetizer"
    },
    {
        "title": "Homemade Kikiam",
        "recipe-link": "https://www.kawalingpinoy.com/homemade-kikiam/",
        "image": "https://www.kawalingpinoy.com/wp-content/uploads/2019/07/homemade-kikiam-4-680x884.jpg",
        "meal": "appetizer"
    },
    {
        "title": "Pork Siomai",
        "recipe-link": "https://www.kawalingpinoy.com/siomai/",
        "image": "https://www.kawalingpinoy.com/wp-content/uploads/2019/05/siomai-4-680x884.jpg",
        "meal": "appetizer"
    },
    {
        "title": "Baked Tahong with Sweet Chili-Mayo Topping",
        "recipe-link": "https://www.kawalingpinoy.com/baked-tahong-with-sweet-chili-mayo-topping/",
        "image": "https://www.kawalingpinoy.com/wp-content/uploads/2019/04/creamy-baked-tahong-1-680x884.jpg",
        "meal": "appetizer"
    },
    {
        "title": "Pork Chicharon",
        "recipe-link": "https://www.kawalingpinoy.com/pork-chicharon/",
        "image": "https://www.kawalingpinoy.com/wp-content/uploads/2019/03/pork-chicharon-1-1-680x884.jpg",
        "meal": "appetizer"
    },
    {
        "title": "Southwestern Chicken Egg Rolls",
        "recipe-link": "https://www.kawalingpinoy.com/southwestern-chicken-egg-rolls/",
        "image": "https://www.kawalingpinoy.com/wp-content/uploads/2019/02/southwestern-chicken-egg-rolls-6-1.jpg",
        "meal": "appetizer"
    },
    {
        "title": "Lumpiang Prito with Pork",
        "recipe-link": "https://www.kawalingpinoy.com/lumpiang-prito-with-pork/",
        "image": "https://www.kawalingpinoy.com/wp-content/uploads/2019/01/crispy-lumpiang-prito-with-pork-1-680x884.jpg",
        "meal": "appetizer"
    },
    {
        "title": "Chicken Sisig",
        "recipe-link": "https://www.kawalingpinoy.com/chicken-sisig/",
        "image": "https://www.kawalingpinoy.com/wp-content/uploads/2018/12/spicy-chicken-sisig-680x884.jpg",
        "meal": "appetizer"
    },
    {
        "title": "Plum Sauce Chicken Lollipops",
        "recipe-link": "https://www.kawalingpinoy.com/plum-sauce-chicken-lollipops/",
        "image": "https://www.kawalingpinoy.com/wp-content/uploads/2015/03/plum-sauce-chicken-lollipops-1-2.jpg",
        "meal": "appetizer"
    },
    {
        "title": "Steamed Spareribs with Black Beans",
        "recipe-link": "https://www.kawalingpinoy.com/steamed-spareribs-with-black-beans/",
        "image": "https://www.kawalingpinoy.com/wp-content/uploads/2018/10/asian-steamed-spare-ribs-7-680x884.jpg",
        "meal": "appetizer"
    },
    {
        "title": "Sizzling Balut",
        "recipe-link": "https://www.kawalingpinoy.com/sizzling-balut/",
        "image": "https://www.kawalingpinoy.com/wp-content/uploads/2018/08/sizzling-balut-8-680x884.jpg",
        "meal": "appetizer"
    },
    {
        "title": "Minced Chicken in Lettuce Cups",
        "recipe-link": "https://www.kawalingpinoy.com/minced-chicken-in-lettuce-wraps/",
        "image": "https://www.kawalingpinoy.com/wp-content/uploads/2016/04/minced-chicken-in-lettuce-cups-4-1.jpg",
        "meal": "appetizer"
    },
    {
        "title": "Ukoy na Togue",
        "recipe-link": "https://www.kawalingpinoy.com/ukoy-na-togue/",
        "image": "https://www.kawalingpinoy.com/wp-content/uploads/2018/03/crispy-ukoy-na-togue-2-680x884.jpg",
        "meal": "appetizer"
    },
    {
        "title": "Crispy Fried Calamari",
        "recipe-link": "https://www.kawalingpinoy.com/fried-calamari/",
        "image": "https://www.kawalingpinoy.com/wp-content/uploads/2017/10/crispy-fried-calamari-3-680x884.jpg",
        "meal": "appetizer"
    },
    {
        "title": "Lumpiang Togue",
        "recipe-link": "https://www.kawalingpinoy.com/lumpiang-togue/",
        "image": "https://www.kawalingpinoy.com/wp-content/uploads/2017/05/prito-lumpiang-togue-680x884.jpg",
        "meal": "appetizer"
    },
    {
        "title": "Lumpiang Galunggong",
        "recipe-link": "https://www.kawalingpinoy.com/lumpiang-galunggong/",
        "image": "https://www.kawalingpinoy.com/wp-content/uploads/2017/03/lumpiang-galunggong-13-680x884.jpg",
        "meal": "appetizer"
    },
    {
        "title": "Bangus Sisig",
        "recipe-link": "https://www.kawalingpinoy.com/bangus-sisig/",
        "image": "https://www.kawalingpinoy.com/wp-content/uploads/2017/03/sisig-bangus-2-680x884.jpg",
        "meal": "appetizer"
    },
    {
        "title": "Homemade Fish Balls with Spicy Fish Ball Sauce",
        "recipe-link": "https://www.kawalingpinoy.com/homemade-fish-balls-with-spicy-fish-ball-sauce/",
        "image": "https://www.kawalingpinoy.com/wp-content/uploads/2016/09/homemade-fish-balls-6-1.jpg",
        "meal": "appetizer"
    },
    {
        "title": "BBQ Pork Ears",
        "recipe-link": "https://www.kawalingpinoy.com/bbq-pork-ears/",
        "image": "https://www.kawalingpinoy.com/wp-content/uploads/2016/03/bbq-pork-ears-2-680x884.jpg",
        "meal": "appetizer"
    },
    {
        "title": "Chizza",
        "recipe-link": "https://www.kawalingpinoy.com/chizza/",
        "image": "https://www.kawalingpinoy.com/wp-content/uploads/2015/07/chizza71.jpg",
        "meal": "appetizer"
    },
    {
        "title": "Dynamite Lumpia",
        "recipe-link": "https://www.kawalingpinoy.com/dynamite-lumpia/",
        "image": "https://www.kawalingpinoy.com/wp-content/uploads/2015/04/crispy-dynamite-lumpia-2-680x884.jpg",
        "meal": "appetizer"
    },
    {
        "title": "Longganisa Wontons",
        "recipe-link": "https://www.kawalingpinoy.com/longganisa-wontons/",
        "image": "https://www.kawalingpinoy.com/wp-content/uploads/2014/09/longganisawonton11.jpg",
        "meal": "appetizer"
    },
    {
        "title": "Honey Bagoong Chicken Wings",
        "recipe-link": "https://www.kawalingpinoy.com/honey-bagoong-chicken-wings/",
        "image": "https://www.kawalingpinoy.com/wp-content/uploads/2014/08/honeybagoongchickenwings3a1.jpg",
        "meal": "appetizer"
    }
]