[
    {
        "title": "Pinipig Shortbread Cookies",
        "recipe-link": "https://www.kawalingpinoy.com/pinipig-shortbread-cookies/",
        "image": "https://www.kawalingpinoy.com/wp-content/uploads/2015/04/Pinipig-Shortbread-Cookies-6-680x884.jpg",
        "meal": "bread/baked goods"
    },
    {
        "title": "Buko Pie (Filipino Coconut Pie)",
        "recipe-link": "https://www.kawalingpinoy.com/buko-pie/",
        "image": "https://www.kawalingpinoy.com/wp-content/uploads/2018/05/buko-pie-16-680x884.jpg",
        "meal": "bread/baked goods"
    },
    {
        "title": "Crema de Fruta",
        "recipe-link": "https://www.kawalingpinoy.com/crema-de-fruta/",
        "image": "https://www.kawalingpinoy.com/wp-content/uploads/2017/11/crema-de-fruta-9-680x884.jpg",
        "meal": "bread/baked goods"
    },
    {
        "title": "Yema Bread Rolls",
        "recipe-link": "https://www.kawalingpinoy.com/yema-bread-rolls/",
        "image": "https://www.kawalingpinoy.com/wp-content/uploads/2017/09/yema-bread-rolls-6-1-680x884.jpg",
        "meal": "bread/baked goods"
    },
    {
        "title": "Pandesal",
        "recipe-link": "https://www.kawalingpinoy.com/pandesal/",
        "image": "https://www.kawalingpinoy.com/wp-content/uploads/2013/12/pandesal-bread-680x884.jpg",
        "meal": "bread/baked goods"
    },
    {
        "title": "Beef Empanada",
        "recipe-link": "https://www.kawalingpinoy.com/beef-empanada/",
        "image": "https://www.kawalingpinoy.com/wp-content/uploads/2019/03/beef-empanada-11-680x884.jpg",
        "meal": "bread/baked goods"
    },
    {
        "title": "Banana Pandan Bread",
        "recipe-link": "https://www.kawalingpinoy.com/banana-pandan-bread/",
        "image": "https://www.kawalingpinoy.com/wp-content/uploads/2019/09/banana-pandan-bread-with-cashews-2-680x884.jpg",
        "meal": "bread/baked goods"
    },
    {
        "title": "Corned Beef Pandesal",
        "recipe-link": "https://www.kawalingpinoy.com/corned-beef-pandesal/",
        "image": "https://www.kawalingpinoy.com/wp-content/uploads/2017/10/corned-beef-pandesal-buns-1-680x884.jpg",
        "meal": "bread/baked goods"
    },
    {
        "title": "Pineapple Upside Down Cake",
        "recipe-link": "https://www.kawalingpinoy.com/pineapple-upside-down-cake/",
        "image": "https://www.kawalingpinoy.com/wp-content/uploads/2020/07/pineapple-upside-down-cake-14-680x884.jpg",
        "meal": "bread/baked goods"
    },
    {
        "title": "Ube Mamon",
        "recipe-link": "https://www.kawalingpinoy.com/ube-mamon/",
        "image": "https://www.kawalingpinoy.com/wp-content/uploads/2017/07/mamon-ube-1-680x884.jpg",
        "meal": "bread/baked goods"
    },
    {
        "title": "Mango Bread Loaf",
        "recipe-link": "https://www.kawalingpinoy.com/mango-bread-loaf/",
        "image": "https://www.kawalingpinoy.com/wp-content/uploads/2020/04/mango-bread-loaf-6-680x884.jpg",
        "meal": "bread/baked goods"
    },
    {
        "title": "Biscocho",
        "recipe-link": "https://www.kawalingpinoy.com/biscocho/",
        "image": "https://www.kawalingpinoy.com/wp-content/uploads/2019/03/homemade-biscocho-3-680x884.jpg",
        "meal": "bread/baked goods"
    },
    {
        "title": "Royal Bibingka",
        "recipe-link": "https://www.kawalingpinoy.com/royal-bibingka/",
        "image": "https://www.kawalingpinoy.com/wp-content/uploads/2015/11/royal-bibingka-5-680x884.jpg",
        "meal": "bread/baked goods"
    },
    {
        "title": "Kababayan",
        "recipe-link": "https://www.kawalingpinoy.com/kababayan/",
        "image": "https://www.kawalingpinoy.com/wp-content/uploads/2021/09/kababayan-2-680x884.jpg",
        "meal": "bread/baked goods"
    },
    {
        "title": "Cebuana Torta Cake",
        "recipe-link": "https://www.kawalingpinoy.com/cebuana-torta-cake/",
        "image": "https://www.kawalingpinoy.com/wp-content/uploads/2021/09/torta-cebuana-5-680x884.jpg",
        "meal": "bread/baked goods"
    },
    {
        "title": "Corned Beef Hash Breakfast Pizza",
        "recipe-link": "https://www.kawalingpinoy.com/corned-beef-hash-breakfast-pizza/",
        "image": "https://www.kawalingpinoy.com/wp-content/uploads/2016/08/corned-beef-hash-breakfast-pizza-4-680x884.jpg",
        "meal": "bread/baked goods"
    },
    {
        "title": "Uraro Cookies",
        "recipe-link": "https://www.kawalingpinoy.com/uraro-cookies/",
        "image": "https://www.kawalingpinoy.com/wp-content/uploads/2021/08/uraro-cookies-3-680x884.jpg",
        "meal": "bread/baked goods"
    },
    {
        "title": "Monay",
        "recipe-link": "https://www.kawalingpinoy.com/monay/",
        "image": "https://www.kawalingpinoy.com/wp-content/uploads/2021/08/monay-4-680x884.jpg",
        "meal": "bread/baked goods"
    },
    {
        "title": "Lengua de Gato",
        "recipe-link": "https://www.kawalingpinoy.com/lengua-de-gato/",
        "image": "https://www.kawalingpinoy.com/wp-content/uploads/2021/07/lengua-de-gato-6-680x884.jpg",
        "meal": "bread/baked goods"
    },
    {
        "title": "Otap",
        "recipe-link": "https://www.kawalingpinoy.com/otap/",
        "image": "https://www.kawalingpinoy.com/wp-content/uploads/2021/05/otap-5-680x884.jpg",
        "meal": "bread/baked goods"
    },
    {
        "title": "Moist Chocolate Cupcakes with Mocha Buttercream Frosting",
        "recipe-link": "https://www.kawalingpinoy.com/chocolate-cupcakes-mocha-buttercream-frosting/",
        "image": "https://www.kawalingpinoy.com/wp-content/uploads/2019/02/chocolate-cupcakes-with-mocha-buttercream-4-680x884.jpg",
        "meal": "bread/baked goods"
    },
    {
        "title": "Tropical Magic Bars",
        "recipe-link": "https://www.kawalingpinoy.com/tropical-magic-bars/",
        "image": "https://www.kawalingpinoy.com/wp-content/uploads/2020/09/tropical-magic-bars-4-1.jpg",
        "meal": "bread/baked goods"
    },
    {
        "title": "Mango Bravo Cake",
        "recipe-link": "https://www.kawalingpinoy.com/mango-bravo-cake/",
        "image": "https://www.kawalingpinoy.com/wp-content/uploads/2020/08/mango-bravo-cake-5-1-680x884.jpg",
        "meal": "bread/baked goods"
    },
    {
        "title": "Chocolate Pandesal with Nutella Filling",
        "recipe-link": "https://www.kawalingpinoy.com/chocolate-pandesal-with-nutella-filling/",
        "image": "https://www.kawalingpinoy.com/wp-content/uploads/2020/08/chocolate-pandesal-with-nutella-filling-2-680x884.jpg",
        "meal": "bread/baked goods"
    },
    {
        "title": "Pandan Pandesal with Ube Halaya Filling",
        "recipe-link": "https://www.kawalingpinoy.com/pandan-pandesal-with-ube-halaya-filling/",
        "image": "https://www.kawalingpinoy.com/wp-content/uploads/2020/07/pandan-pandesal-1-1-680x884.jpg",
        "meal": "bread/baked goods"
    },
    {
        "title": "Siopao Bola-Bola",
        "recipe-link": "https://www.kawalingpinoy.com/siopao-bola-bola/",
        "image": "https://www.kawalingpinoy.com/wp-content/uploads/2020/07/siopao-bola-bola-3-1-680x884.jpg",
        "meal": "bread/baked goods"
    },
    {
        "title": "Siopao Asado",
        "recipe-link": "https://www.kawalingpinoy.com/siopao-asado/",
        "image": "https://www.kawalingpinoy.com/wp-content/uploads/2015/03/siopao-asado-4-1-680x884.jpg",
        "meal": "bread/baked goods"
    },
    {
        "title": "Kalihim",
        "recipe-link": "https://www.kawalingpinoy.com/kalihim/",
        "image": "https://www.kawalingpinoy.com/wp-content/uploads/2020/07/pan-de-regla-680x884.jpg",
        "meal": "bread/baked goods"
    },
    {
        "title": "Red Velvet Pandesal",
        "recipe-link": "https://www.kawalingpinoy.com/red-velvet-pandesal/",
        "image": "https://www.kawalingpinoy.com/wp-content/uploads/2020/06/red-velvet-pandesal-2-1-680x884.jpg",
        "meal": "bread/baked goods"
    },
    {
        "title": "Ube Cheese Pandesal",
        "recipe-link": "https://www.kawalingpinoy.com/ube-cheese-pandesal/",
        "image": "https://www.kawalingpinoy.com/wp-content/uploads/2020/06/ube-pandesal-4-1-680x884.jpg",
        "meal": "bread/baked goods"
    },
    {
        "title": "Calamansi Muffins",
        "recipe-link": "https://www.kawalingpinoy.com/calamansi-muffins/",
        "image": "https://www.kawalingpinoy.com/wp-content/uploads/2020/01/calamansi-muffins-with-citrus-glaze-6-680x884.jpg",
        "meal": "bread/baked goods"
    },
    {
        "title": "Christmas Fruitcake",
        "recipe-link": "https://www.kawalingpinoy.com/christmas-fruitcake/",
        "image": "https://www.kawalingpinoy.com/wp-content/uploads/2019/12/fruitcake-1-1-680x884.jpg",
        "meal": "bread/baked goods"
    },
    {
        "title": "Impossible Chocolate Flan Cake",
        "recipe-link": "https://www.kawalingpinoy.com/impossible-chocolate-flan-cake/",
        "image": "https://www.kawalingpinoy.com/wp-content/uploads/2019/10/impossible-chococolate-flan-cake-6-1-680x884.jpg",
        "meal": "bread/baked goods"
    },
    {
        "title": "Cheater's Siopao Bola Bola",
        "recipe-link": "https://www.kawalingpinoy.com/cheaters-siopao-bola-bola/",
        "image": "https://www.kawalingpinoy.com/wp-content/uploads/2013/07/cheaters-siopao-bola-bola-7-1-680x884.jpg",
        "meal": "bread/baked goods"
    },
    {
        "title": "Black Forest Swiss Roll Cake",
        "recipe-link": "https://www.kawalingpinoy.com/black-forest-swiss-roll-cake/",
        "image": "https://www.kawalingpinoy.com/wp-content/uploads/2019/05/Black-forest-swiss-roll-14-1-680x884.jpg",
        "meal": "bread/baked goods"
    },
    {
        "title": "Bicho-Bicho",
        "recipe-link": "https://www.kawalingpinoy.com/bicho-bicho/",
        "image": "https://www.kawalingpinoy.com/wp-content/uploads/2019/05/bicho-bicho-2-1-680x884.jpg",
        "meal": "bread/baked goods"
    },
    {
        "title": "Silvanas",
        "recipe-link": "https://www.kawalingpinoy.com/silvanas/",
        "image": "https://www.kawalingpinoy.com/wp-content/uploads/2019/04/silvanas-3-1-680x884.jpg",
        "meal": "bread/baked goods"
    },
    {
        "title": "Sans Rival",
        "recipe-link": "https://www.kawalingpinoy.com/sans-rival/",
        "image": "https://www.kawalingpinoy.com/wp-content/uploads/2019/04/sans-rival-3-1.jpg",
        "meal": "bread/baked goods"
    },
    {
        "title": "Mini Egg Pies",
        "recipe-link": "https://www.kawalingpinoy.com/mini-egg-pies/",
        "image": "https://www.kawalingpinoy.com/wp-content/uploads/2019/03/mini-egg-pies-1-1-680x884.jpg",
        "meal": "bread/baked goods"
    },
    {
        "title": "Sweet Potato Dinner Rolls",
        "recipe-link": "https://www.kawalingpinoy.com/sweet-potato-dinner-rolls/",
        "image": "https://www.kawalingpinoy.com/wp-content/uploads/2018/08/sweet-potato-dinner-rolls-4-1-680x884.jpg",
        "meal": "bread/baked goods"
    },
    {
        "title": "Yema Cake",
        "recipe-link": "https://www.kawalingpinoy.com/yema-cake/",
        "image": "https://www.kawalingpinoy.com/wp-content/uploads/2018/07/cheesy-yema-cake-3-680x884.jpg",
        "meal": "bread/baked goods"
    },
    {
        "title": "Monggo Loaf Bread",
        "recipe-link": "https://www.kawalingpinoy.com/monggo-loaf-bread/",
        "image": "https://www.kawalingpinoy.com/wp-content/uploads/2018/05/monggo-loaf-bread-680x884.jpg",
        "meal": "bread/baked goods"
    },
    {
        "title": "Ube Crinkles (Purple Yam Crinkles)",
        "recipe-link": "https://www.kawalingpinoy.com/ube-crinkles/",
        "image": "https://www.kawalingpinoy.com/wp-content/uploads/2018/05/ube-crinkle-cookies-4-680x884.jpg",
        "meal": "bread/baked goods"
    },
    {
        "title": "Pianono (Filipino Sponge Cake Roll)",
        "recipe-link": "https://www.kawalingpinoy.com/pianono/",
        "image": "https://www.kawalingpinoy.com/wp-content/uploads/2018/04/filipino-pianono-2-680x884.jpg",
        "meal": "bread/baked goods"
    },
    {
        "title": "Pan de Coco",
        "recipe-link": "https://www.kawalingpinoy.com/pan-de-coco/",
        "image": "https://www.kawalingpinoy.com/wp-content/uploads/2018/04/filipino-pan-de-coco-680x884.jpg",
        "meal": "bread/baked goods"
    },
    {
        "title": "Filipino Coconut Macaroons",
        "recipe-link": "https://www.kawalingpinoy.com/filipino-coconut-macaroons/",
        "image": "https://www.kawalingpinoy.com/wp-content/uploads/2017/05/easy-filipino-coconut-macaroons-2-680x884.jpg",
        "meal": "bread/baked goods"
    },
    {
        "title": "Hawaiian Bread Pudding",
        "recipe-link": "https://www.kawalingpinoy.com/hawaiian-bread-pudding/",
        "image": "https://www.kawalingpinoy.com/wp-content/uploads/2016/09/hawaiian-bread-pudding-2-680x884.jpg",
        "meal": "bread/baked goods"
    },
    {
        "title": "Cheese Puto",
        "recipe-link": "https://www.kawalingpinoy.com/cheese-puto/",
        "image": "https://www.kawalingpinoy.com/wp-content/uploads/2014/11/cheese-puto-5-1-680x884.jpg",
        "meal": "bread/baked goods"
    },
    {
        "title": "Cheese Cupcakes",
        "recipe-link": "https://www.kawalingpinoy.com/cheese-cupcakes/",
        "image": "https://www.kawalingpinoy.com/wp-content/uploads/2013/08/cheese-cupcakes-5-1-680x884.jpg",
        "meal": "bread/baked goods"
    }
]